{"cv32e40p": {"8a3345cd": {"codeEntityRedundancyNumForLocal": 8, "codeEntitySumForLobal": 24, "commitRedundancyForLocal": false, "codeEntityRedundancyNumForGlobal": 8, "codeEntitySumForGlobal": 24, "commitRedundancyForGlobal": false}, "d5c526d9": {"codeEntityRedundancyNumForLocal": 173, "codeEntitySumForLobal": 770, "commitRedundancyForLocal": false, "codeEntityRedundancyNumForGlobal": 187, "codeEntitySumForGlobal": 770, "commitRedundancyForGlobal": false}, "b9cce7f1": {"codeEntityRedundancyNumForLocal": 0, "codeEntitySumForLobal": 1, "commitRedundancyForLocal": false, "codeEntityRedundancyNumForGlobal": 0, "codeEntitySumForGlobal": 1, "commitRedundancyForGlobal": false}, "fabe3b43": {"codeEntityRedundancyNumForLocal": 22, "codeEntitySumForLobal": 108, "commitRedundancyForLocal": false, "codeEntityRedundancyNumForGlobal": 23, "codeEntitySumForGlobal": 108, "commitRedundancyForGlobal": false}, "7e9c3744": {"codeEntityRedundancyNumForLocal": 0, "codeEntitySumForLobal": 2, "commitRedundancyForLocal": false, "codeEntityRedundancyNumForGlobal": 0, "codeEntitySumForGlobal": 2, "commitRedundancyForGlobal": false}, "70b666a2": {"codeEntityRedundancyNumForLocal": 7, "codeEntitySumForLobal": 60, "commitRedundancyForLocal": false, "codeEntityRedundancyNumForGlobal": 7, "codeEntitySumForGlobal": 60, "commitRedundancyForGlobal": false}, "d6ad52f5": {"codeEntityRedundancyNumForLocal": 0, "codeEntitySumForLobal": 2, "commitRedundancyForLocal": false, "codeEntityRedundancyNumForGlobal": 0, "codeEntitySumForGlobal": 2, "commitRedundancyForGlobal": false}, "f9354dc9": {"codeEntityRedundancyNumForLocal": 3, "codeEntitySumForLobal": 8, "commitRedundancyForLocal": false, "codeEntityRedundancyNumForGlobal": 3, "codeEntitySumForGlobal": 8, "commitRedundancyForGlobal": false}, "a2e44ad3": {"codeEntityRedundancyNumForLocal": 83, "codeEntitySumForLobal": 101, "commitRedundancyForLocal": false, "codeEntityRedundancyNumForGlobal": 83, "codeEntitySumForGlobal": 101, "commitRedundancyForGlobal": false}, "8ccbcdcb": {"codeEntityRedundancyNumForLocal": 6, "codeEntitySumForLobal": 18, "commitRedundancyForLocal": false, "codeEntityRedundancyNumForGlobal": 6, "codeEntitySumForGlobal": 18, "commitRedundancyForGlobal": false}, "5ad84f64": {"codeEntityRedundancyNumForLocal": 20, "codeEntitySumForLobal": 46, "commitRedundancyForLocal": false, "codeEntityRedundancyNumForGlobal": 20, "codeEntitySumForGlobal": 46, "commitRedundancyForGlobal": false}, "1d59c146": {"codeEntityRedundancyNumForLocal": 15, "codeEntitySumForLobal": 27, "commitRedundancyForLocal": false, "codeEntityRedundancyNumForGlobal": 15, "codeEntitySumForGlobal": 27, "commitRedundancyForGlobal": false}, "c2f9ff51": {"codeEntityRedundancyNumForLocal": 136, "codeEntitySumForLobal": 140, "commitRedundancyForLocal": false, "codeEntityRedundancyNumForGlobal": 136, "codeEntitySumForGlobal": 140, "commitRedundancyForGlobal": false}, "3f7b9e01": {"codeEntityRedundancyNumForLocal": 10, "codeEntitySumForLobal": 14, "commitRedundancyForLocal": false, "codeEntityRedundancyNumForGlobal": 10, "codeEntitySumForGlobal": 14, "commitRedundancyForGlobal": false}, "525268bc": {"codeEntityRedundancyNumForLocal": 1810, "codeEntitySumForLobal": 2021, "commitRedundancyForLocal": false, "codeEntityRedundancyNumForGlobal": 1819, "codeEntitySumForGlobal": 2021, "commitRedundancyForGlobal": false}, "d1e39c2a": {"codeEntityRedundancyNumForLocal": 1793, "codeEntitySumForLobal": 1920, "commitRedundancyForLocal": false, "codeEntityRedundancyNumForGlobal": 1793, "codeEntitySumForGlobal": 1920, "commitRedundancyForGlobal": false}, "e2c86c9f": {"codeEntityRedundancyNumForLocal": 6, "codeEntitySumForLobal": 20, "commitRedundancyForLocal": false, "codeEntityRedundancyNumForGlobal": 8, "codeEntitySumForGlobal": 20, "commitRedundancyForGlobal": false}, "4fe515fd": {"codeEntityRedundancyNumForLocal": 93, "codeEntitySumForLobal": 282, "commitRedundancyForLocal": false, "codeEntityRedundancyNumForGlobal": 99, "codeEntitySumForGlobal": 282, "commitRedundancyForGlobal": false}, "c0c6549a": {"codeEntityRedundancyNumForLocal": 224, "codeEntitySumForLobal": 290, "commitRedundancyForLocal": false, "codeEntityRedundancyNumForGlobal": 229, "codeEntitySumForGlobal": 290, "commitRedundancyForGlobal": false}, "edf4060f": {"codeEntityRedundancyNumForLocal": 2, "codeEntitySumForLobal": 10, "commitRedundancyForLocal": false, "codeEntityRedundancyNumForGlobal": 2, "codeEntitySumForGlobal": 10, "commitRedundancyForGlobal": false}, "c304b1dd": {"codeEntityRedundancyNumForLocal": 879, "codeEntitySumForLobal": 2684, "commitRedundancyForLocal": false, "codeEntityRedundancyNumForGlobal": 879, "codeEntitySumForGlobal": 2684, "commitRedundancyForGlobal": false}, "3f3197d1": {"codeEntityRedundancyNumForLocal": 8, "codeEntitySumForLobal": 18, "commitRedundancyForLocal": false, "codeEntityRedundancyNumForGlobal": 8, "codeEntitySumForGlobal": 18, "commitRedundancyForGlobal": false}, "460a49f1": {"codeEntityRedundancyNumForLocal": 784, "codeEntitySumForLobal": 2948, "commitRedundancyForLocal": false, "codeEntityRedundancyNumForGlobal": 798, "codeEntitySumForGlobal": 2948, "commitRedundancyForGlobal": false}, "89884e51": {"codeEntityRedundancyNumForLocal": 13, "codeEntitySumForLobal": 26, "commitRedundancyForLocal": false, "codeEntityRedundancyNumForGlobal": 13, "codeEntitySumForGlobal": 26, "commitRedundancyForGlobal": false}, "744e5079": {"codeEntityRedundancyNumForLocal": 114, "codeEntitySumForLobal": 147, "commitRedundancyForLocal": false, "codeEntityRedundancyNumForGlobal": 114, "codeEntitySumForGlobal": 147, "commitRedundancyForGlobal": false}, "daa9cddb": {"codeEntityRedundancyNumForLocal": 1, "codeEntitySumForLobal": 1, "commitRedundancyForLocal": true, "codeEntityRedundancyNumForGlobal": 1, "codeEntitySumForGlobal": 1, "commitRedundancyForGlobal": true}, "dd1eeca0": {"codeEntityRedundancyNumForLocal": 181, "codeEntitySumForLobal": 699, "commitRedundancyForLocal": false, "codeEntityRedundancyNumForGlobal": 195, "codeEntitySumForGlobal": 699, "commitRedundancyForGlobal": false}, "c9b37223": {"codeEntityRedundancyNumForLocal": 0, "codeEntitySumForLobal": 0, "commitRedundancyForLocal": true, "codeEntityRedundancyNumForGlobal": 0, "codeEntitySumForGlobal": 0, "commitRedundancyForGlobal": true}, "c3405e8b": {"codeEntityRedundancyNumForLocal": 4, "codeEntitySumForLobal": 15, "commitRedundancyForLocal": false, "codeEntityRedundancyNumForGlobal": 4, "codeEntitySumForGlobal": 15, "commitRedundancyForGlobal": false}, "f38bd364": {"codeEntityRedundancyNumForLocal": 6, "codeEntitySumForLobal": 21, "commitRedundancyForLocal": false, "codeEntityRedundancyNumForGlobal": 8, "codeEntitySumForGlobal": 21, "commitRedundancyForGlobal": false}, "448d8cde": {"codeEntityRedundancyNumForLocal": 0, "codeEntitySumForLobal": 14, "commitRedundancyForLocal": false, "codeEntityRedundancyNumForGlobal": 0, "codeEntitySumForGlobal": 14, "commitRedundancyForGlobal": false}, "b98aad84": {"codeEntityRedundancyNumForLocal": 0, "codeEntitySumForLobal": 3, "commitRedundancyForLocal": false, "codeEntityRedundancyNumForGlobal": 0, "codeEntitySumForGlobal": 3, "commitRedundancyForGlobal": false}, "d67895e8": {"codeEntityRedundancyNumForLocal": 0, "codeEntitySumForLobal": 0, "commitRedundancyForLocal": true, "codeEntityRedundancyNumForGlobal": 0, "codeEntitySumForGlobal": 0, "commitRedundancyForGlobal": true}, "ecaa6076": {"codeEntityRedundancyNumForLocal": 2, "codeEntitySumForLobal": 18, "commitRedundancyForLocal": false, "codeEntityRedundancyNumForGlobal": 2, "codeEntitySumForGlobal": 18, "commitRedundancyForGlobal": false}, "1b2b29bc": {"codeEntityRedundancyNumForLocal": 6, "codeEntitySumForLobal": 6, "commitRedundancyForLocal": true, "codeEntityRedundancyNumForGlobal": 6, "codeEntitySumForGlobal": 6, "commitRedundancyForGlobal": true}, "feb53aef": {"codeEntityRedundancyNumForLocal": 3, "codeEntitySumForLobal": 11, "commitRedundancyForLocal": false, "codeEntityRedundancyNumForGlobal": 3, "codeEntitySumForGlobal": 11, "commitRedundancyForGlobal": false}, "17cc76f3": {"codeEntityRedundancyNumForLocal": 7, "codeEntitySumForLobal": 32, "commitRedundancyForLocal": false, "codeEntityRedundancyNumForGlobal": 10, "codeEntitySumForGlobal": 32, "commitRedundancyForGlobal": false}, "162529d7": {"codeEntityRedundancyNumForLocal": 304, "codeEntitySumForLobal": 421, "commitRedundancyForLocal": false, "codeEntityRedundancyNumForGlobal": 311, "codeEntitySumForGlobal": 421, "commitRedundancyForGlobal": false}, "ab4b5b17": {"codeEntityRedundancyNumForLocal": 198, "codeEntitySumForLobal": 748, "commitRedundancyForLocal": false, "codeEntityRedundancyNumForGlobal": 259, "codeEntitySumForGlobal": 748, "commitRedundancyForGlobal": false}, "db82a7ab": {"codeEntityRedundancyNumForLocal": 0, "codeEntitySumForLobal": 2, "commitRedundancyForLocal": false, "codeEntityRedundancyNumForGlobal": 0, "codeEntitySumForGlobal": 2, "commitRedundancyForGlobal": false}, "cd659a13": {"codeEntityRedundancyNumForLocal": 153, "codeEntitySumForLobal": 485, "commitRedundancyForLocal": false, "codeEntityRedundancyNumForGlobal": 169, "codeEntitySumForGlobal": 485, "commitRedundancyForGlobal": false}, "93924acf": {"codeEntityRedundancyNumForLocal": 10, "codeEntitySumForLobal": 10, "commitRedundancyForLocal": true, "codeEntityRedundancyNumForGlobal": 10, "codeEntitySumForGlobal": 10, "commitRedundancyForGlobal": true}, "3d957e5f": {"codeEntityRedundancyNumForLocal": 64, "codeEntitySumForLobal": 114, "commitRedundancyForLocal": false, "codeEntityRedundancyNumForGlobal": 64, "codeEntitySumForGlobal": 114, "commitRedundancyForGlobal": false}, "ee17dc0a": {"codeEntityRedundancyNumForLocal": 50, "codeEntitySumForLobal": 634, "commitRedundancyForLocal": false, "codeEntityRedundancyNumForGlobal": 50, "codeEntitySumForGlobal": 634, "commitRedundancyForGlobal": false}, "f40659f1": {"codeEntityRedundancyNumForLocal": 0, "codeEntitySumForLobal": 0, "commitRedundancyForLocal": true, "codeEntityRedundancyNumForGlobal": 0, "codeEntitySumForGlobal": 0, "commitRedundancyForGlobal": true}, "101f455d": {"codeEntityRedundancyNumForLocal": 7, "codeEntitySumForLobal": 98, "commitRedundancyForLocal": false, "codeEntityRedundancyNumForGlobal": 14, "codeEntitySumForGlobal": 98, "commitRedundancyForGlobal": false}, "0274b484": {"codeEntityRedundancyNumForLocal": 1, "codeEntitySumForLobal": 2, "commitRedundancyForLocal": false, "codeEntityRedundancyNumForGlobal": 1, "codeEntitySumForGlobal": 2, "commitRedundancyForGlobal": false}, "10d9a75f": {"codeEntityRedundancyNumForLocal": 16, "codeEntitySumForLobal": 20, "commitRedundancyForLocal": false, "codeEntityRedundancyNumForGlobal": 16, "codeEntitySumForGlobal": 20, "commitRedundancyForGlobal": false}, "669c7ba8": {"codeEntityRedundancyNumForLocal": 3, "codeEntitySumForLobal": 5, "commitRedundancyForLocal": false, "codeEntityRedundancyNumForGlobal": 3, "codeEntitySumForGlobal": 5, "commitRedundancyForGlobal": false}, "841b8b12": {"codeEntityRedundancyNumForLocal": 71, "codeEntitySumForLobal": 93, "commitRedundancyForLocal": false, "codeEntityRedundancyNumForGlobal": 71, "codeEntitySumForGlobal": 93, "commitRedundancyForGlobal": false}, "76afe737": {"codeEntityRedundancyNumForLocal": 4, "codeEntitySumForLobal": 5, "commitRedundancyForLocal": false, "codeEntityRedundancyNumForGlobal": 4, "codeEntitySumForGlobal": 5, "commitRedundancyForGlobal": false}, "8e2daa45": {"codeEntityRedundancyNumForLocal": 25, "codeEntitySumForLobal": 135, "commitRedundancyForLocal": false, "codeEntityRedundancyNumForGlobal": 26, "codeEntitySumForGlobal": 135, "commitRedundancyForGlobal": false}, "9031c5df": {"codeEntityRedundancyNumForLocal": 29, "codeEntitySumForLobal": 59, "commitRedundancyForLocal": false, "codeEntityRedundancyNumForGlobal": 29, "codeEntitySumForGlobal": 59, "commitRedundancyForGlobal": false}, "9be96bda": {"codeEntityRedundancyNumForLocal": 0, "codeEntitySumForLobal": 0, "commitRedundancyForLocal": true, "codeEntityRedundancyNumForGlobal": 0, "codeEntitySumForGlobal": 0, "commitRedundancyForGlobal": true}, "d6f8fe2e": {"codeEntityRedundancyNumForLocal": 70, "codeEntitySumForLobal": 158, "commitRedundancyForLocal": false, "codeEntityRedundancyNumForGlobal": 71, "codeEntitySumForGlobal": 158, "commitRedundancyForGlobal": false}, "cf327713": {"codeEntityRedundancyNumForLocal": 1, "codeEntitySumForLobal": 12, "commitRedundancyForLocal": false, "codeEntityRedundancyNumForGlobal": 1, "codeEntitySumForGlobal": 12, "commitRedundancyForGlobal": false}, "5b90debe": {"codeEntityRedundancyNumForLocal": 2, "codeEntitySumForLobal": 7, "commitRedundancyForLocal": false, "codeEntityRedundancyNumForGlobal": 2, "codeEntitySumForGlobal": 7, "commitRedundancyForGlobal": false}, "6fbd88c6": {"codeEntityRedundancyNumForLocal": 0, "codeEntitySumForLobal": 0, "commitRedundancyForLocal": true, "codeEntityRedundancyNumForGlobal": 0, "codeEntitySumForGlobal": 0, "commitRedundancyForGlobal": true}, "eeb6d109": {"codeEntityRedundancyNumForLocal": 1, "codeEntitySumForLobal": 1, "commitRedundancyForLocal": true, "codeEntityRedundancyNumForGlobal": 1, "codeEntitySumForGlobal": 1, "commitRedundancyForGlobal": true}, "1e1272f8": {"codeEntityRedundancyNumForLocal": 18, "codeEntitySumForLobal": 33, "commitRedundancyForLocal": false, "codeEntityRedundancyNumForGlobal": 18, "codeEntitySumForGlobal": 33, "commitRedundancyForGlobal": false}, "68bb847e": {"codeEntityRedundancyNumForLocal": 23, "codeEntitySumForLobal": 60, "commitRedundancyForLocal": false, "codeEntityRedundancyNumForGlobal": 23, "codeEntitySumForGlobal": 60, "commitRedundancyForGlobal": false}, "66bc864f": {"codeEntityRedundancyNumForLocal": 12, "codeEntitySumForLobal": 29, "commitRedundancyForLocal": false, "codeEntityRedundancyNumForGlobal": 12, "codeEntitySumForGlobal": 29, "commitRedundancyForGlobal": false}, "63000db9": {"codeEntityRedundancyNumForLocal": 0, "codeEntitySumForLobal": 0, "commitRedundancyForLocal": true, "codeEntityRedundancyNumForGlobal": 0, "codeEntitySumForGlobal": 0, "commitRedundancyForGlobal": true}, "586b6aa4": {"codeEntityRedundancyNumForLocal": 50, "codeEntitySumForLobal": 62, "commitRedundancyForLocal": false, "codeEntityRedundancyNumForGlobal": 50, "codeEntitySumForGlobal": 62, "commitRedundancyForGlobal": false}, "f501b332": {"codeEntityRedundancyNumForLocal": 1, "codeEntitySumForLobal": 4, "commitRedundancyForLocal": false, "codeEntityRedundancyNumForGlobal": 1, "codeEntitySumForGlobal": 4, "commitRedundancyForGlobal": false}, "4344de8f": {"codeEntityRedundancyNumForLocal": 9, "codeEntitySumForLobal": 71, "commitRedundancyForLocal": false, "codeEntityRedundancyNumForGlobal": 9, "codeEntitySumForGlobal": 71, "commitRedundancyForGlobal": false}, "7dad509c": {"codeEntityRedundancyNumForLocal": 3, "codeEntitySumForLobal": 7, "commitRedundancyForLocal": false, "codeEntityRedundancyNumForGlobal": 3, "codeEntitySumForGlobal": 7, "commitRedundancyForGlobal": false}, "768d33a4": {"codeEntityRedundancyNumForLocal": 2, "codeEntitySumForLobal": 2, "commitRedundancyForLocal": true, "codeEntityRedundancyNumForGlobal": 2, "codeEntitySumForGlobal": 2, "commitRedundancyForGlobal": true}, "429f485b": {"codeEntityRedundancyNumForLocal": 5, "codeEntitySumForLobal": 19, "commitRedundancyForLocal": false, "codeEntityRedundancyNumForGlobal": 10, "codeEntitySumForGlobal": 19, "commitRedundancyForGlobal": false}, "01822430": {"codeEntityRedundancyNumForLocal": 118, "codeEntitySumForLobal": 213, "commitRedundancyForLocal": false, "codeEntityRedundancyNumForGlobal": 121, "codeEntitySumForGlobal": 213, "commitRedundancyForGlobal": false}, "a5ec2db5": {"codeEntityRedundancyNumForLocal": 198, "codeEntitySumForLobal": 748, "commitRedundancyForLocal": false, "codeEntityRedundancyNumForGlobal": 259, "codeEntitySumForGlobal": 748, "commitRedundancyForGlobal": false}, "1ed24e73": {"codeEntityRedundancyNumForLocal": 21, "codeEntitySumForLobal": 23, "commitRedundancyForLocal": false, "codeEntityRedundancyNumForGlobal": 21, "codeEntitySumForGlobal": 23, "commitRedundancyForGlobal": false}, "ad00d1f4": {"codeEntityRedundancyNumForLocal": 3, "codeEntitySumForLobal": 12, "commitRedundancyForLocal": false, "codeEntityRedundancyNumForGlobal": 3, "codeEntitySumForGlobal": 12, "commitRedundancyForGlobal": false}, "cf0db8ec": {"codeEntityRedundancyNumForLocal": 0, "codeEntitySumForLobal": 2, "commitRedundancyForLocal": false, "codeEntityRedundancyNumForGlobal": 0, "codeEntitySumForGlobal": 2, "commitRedundancyForGlobal": false}, "144209cb": {"codeEntityRedundancyNumForLocal": 1, "codeEntitySumForLobal": 1, "commitRedundancyForLocal": true, "codeEntityRedundancyNumForGlobal": 1, "codeEntitySumForGlobal": 1, "commitRedundancyForGlobal": true}, "a777b94e": {"codeEntityRedundancyNumForLocal": 0, "codeEntitySumForLobal": 3, "commitRedundancyForLocal": false, "codeEntityRedundancyNumForGlobal": 0, "codeEntitySumForGlobal": 3, "commitRedundancyForGlobal": false}, "806065bc": {"codeEntityRedundancyNumForLocal": 3, "codeEntitySumForLobal": 69, "commitRedundancyForLocal": false, "codeEntityRedundancyNumForGlobal": 8, "codeEntitySumForGlobal": 69, "commitRedundancyForGlobal": false}, "df4b88f1": {"codeEntityRedundancyNumForLocal": 1651, "codeEntitySumForLobal": 2781, "commitRedundancyForLocal": false, "codeEntityRedundancyNumForGlobal": 1712, "codeEntitySumForGlobal": 2781, "commitRedundancyForGlobal": false}, "6a4e57b7": {"codeEntityRedundancyNumForLocal": 7, "codeEntitySumForLobal": 60, "commitRedundancyForLocal": false, "codeEntityRedundancyNumForGlobal": 7, "codeEntitySumForGlobal": 60, "commitRedundancyForGlobal": false}, "66e8c238": {"codeEntityRedundancyNumForLocal": 72, "codeEntitySumForLobal": 398, "commitRedundancyForLocal": false, "codeEntityRedundancyNumForGlobal": 81, "codeEntitySumForGlobal": 398, "commitRedundancyForGlobal": false}, "a5cb939f": {"codeEntityRedundancyNumForLocal": 1, "codeEntitySumForLobal": 1, "commitRedundancyForLocal": true, "codeEntityRedundancyNumForGlobal": 1, "codeEntitySumForGlobal": 1, "commitRedundancyForGlobal": true}, "7f8389cb": {"codeEntityRedundancyNumForLocal": 1, "codeEntitySumForLobal": 1, "commitRedundancyForLocal": true, "codeEntityRedundancyNumForGlobal": 1, "codeEntitySumForGlobal": 1, "commitRedundancyForGlobal": true}, "83aaecca": {"codeEntityRedundancyNumForLocal": 4, "codeEntitySumForLobal": 4, "commitRedundancyForLocal": true, "codeEntityRedundancyNumForGlobal": 4, "codeEntitySumForGlobal": 4, "commitRedundancyForGlobal": true}, "d4c92aaf": {"codeEntityRedundancyNumForLocal": 227, "codeEntitySumForLobal": 604, "commitRedundancyForLocal": false, "codeEntityRedundancyNumForGlobal": 230, "codeEntitySumForGlobal": 604, "commitRedundancyForGlobal": false}, "65365073": {"codeEntityRedundancyNumForLocal": 4, "codeEntitySumForLobal": 22, "commitRedundancyForLocal": false, "codeEntityRedundancyNumForGlobal": 4, "codeEntitySumForGlobal": 22, "commitRedundancyForGlobal": false}, "6f90336b": {"codeEntityRedundancyNumForLocal": 23, "codeEntitySumForLobal": 52, "commitRedundancyForLocal": false, "codeEntityRedundancyNumForGlobal": 23, "codeEntitySumForGlobal": 52, "commitRedundancyForGlobal": false}, "7078fa85": {"codeEntityRedundancyNumForLocal": 15, "codeEntitySumForLobal": 70, "commitRedundancyForLocal": false, "codeEntityRedundancyNumForGlobal": 15, "codeEntitySumForGlobal": 70, "commitRedundancyForGlobal": false}, "33fe574e": {"codeEntityRedundancyNumForLocal": 2, "codeEntitySumForLobal": 31, "commitRedundancyForLocal": false, "codeEntityRedundancyNumForGlobal": 2, "codeEntitySumForGlobal": 31, "commitRedundancyForGlobal": false}, "6065bba0": {"codeEntityRedundancyNumForLocal": 2560, "codeEntitySumForLobal": 3517, "commitRedundancyForLocal": false, "codeEntityRedundancyNumForGlobal": 2560, "codeEntitySumForGlobal": 3517, "commitRedundancyForGlobal": false}, "afa2b0f1": {"codeEntityRedundancyNumForLocal": 0, "codeEntitySumForLobal": 15, "commitRedundancyForLocal": false, "codeEntityRedundancyNumForGlobal": 2, "codeEntitySumForGlobal": 15, "commitRedundancyForGlobal": false}, "d710dc82": {"codeEntityRedundancyNumForLocal": 227, "codeEntitySumForLobal": 604, "commitRedundancyForLocal": false, "codeEntityRedundancyNumForGlobal": 230, "codeEntitySumForGlobal": 604, "commitRedundancyForGlobal": false}, "ee89618b": {"codeEntityRedundancyNumForLocal": 30, "codeEntitySumForLobal": 37, "commitRedundancyForLocal": false, "codeEntityRedundancyNumForGlobal": 30, "codeEntitySumForGlobal": 37, "commitRedundancyForGlobal": false}, "80c1d3fe": {"codeEntityRedundancyNumForLocal": 4, "codeEntitySumForLobal": 11, "commitRedundancyForLocal": false, "codeEntityRedundancyNumForGlobal": 4, "codeEntitySumForGlobal": 11, "commitRedundancyForGlobal": false}, "e624d160": {"codeEntityRedundancyNumForLocal": 4, "codeEntitySumForLobal": 9, "commitRedundancyForLocal": false, "codeEntityRedundancyNumForGlobal": 5, "codeEntitySumForGlobal": 9, "commitRedundancyForGlobal": false}, "650336a1": {"codeEntityRedundancyNumForLocal": 1, "codeEntitySumForLobal": 2, "commitRedundancyForLocal": false, "codeEntityRedundancyNumForGlobal": 1, "codeEntitySumForGlobal": 2, "commitRedundancyForGlobal": false}, "fae8a38c": {"codeEntityRedundancyNumForLocal": 31, "codeEntitySumForLobal": 32, "commitRedundancyForLocal": false, "codeEntityRedundancyNumForGlobal": 31, "codeEntitySumForGlobal": 32, "commitRedundancyForGlobal": false}, "c68152b1": {"codeEntityRedundancyNumForLocal": 4, "codeEntitySumForLobal": 15, "commitRedundancyForLocal": false, "codeEntityRedundancyNumForGlobal": 4, "codeEntitySumForGlobal": 15, "commitRedundancyForGlobal": false}, "491acfe5": {"codeEntityRedundancyNumForLocal": 13, "codeEntitySumForLobal": 13, "commitRedundancyForLocal": true, "codeEntityRedundancyNumForGlobal": 13, "codeEntitySumForGlobal": 13, "commitRedundancyForGlobal": true}, "c4a05338": {"codeEntityRedundancyNumForLocal": 34, "codeEntitySumForLobal": 44, "commitRedundancyForLocal": false, "codeEntityRedundancyNumForGlobal": 34, "codeEntitySumForGlobal": 44, "commitRedundancyForGlobal": false}, "562d14fd": {"codeEntityRedundancyNumForLocal": 5, "codeEntitySumForLobal": 16, "commitRedundancyForLocal": false, "codeEntityRedundancyNumForGlobal": 6, "codeEntitySumForGlobal": 16, "commitRedundancyForGlobal": false}, "cd4b4f99": {"codeEntityRedundancyNumForLocal": 261, "codeEntitySumForLobal": 282, "commitRedundancyForLocal": false, "codeEntityRedundancyNumForGlobal": 261, "codeEntitySumForGlobal": 282, "commitRedundancyForGlobal": false}, "2ba82566": {"codeEntityRedundancyNumForLocal": 0, "codeEntitySumForLobal": 3, "commitRedundancyForLocal": false, "codeEntityRedundancyNumForGlobal": 0, "codeEntitySumForGlobal": 3, "commitRedundancyForGlobal": false}, "67cb33d8": {"codeEntityRedundancyNumForLocal": 0, "codeEntitySumForLobal": 17, "commitRedundancyForLocal": false, "codeEntityRedundancyNumForGlobal": 0, "codeEntitySumForGlobal": 17, "commitRedundancyForGlobal": false}, "06cf9f1d": {"codeEntityRedundancyNumForLocal": 0, "codeEntitySumForLobal": 0, "commitRedundancyForLocal": true, "codeEntityRedundancyNumForGlobal": 0, "codeEntitySumForGlobal": 0, "commitRedundancyForGlobal": true}, "ec5e7a32": {"codeEntityRedundancyNumForLocal": 8, "codeEntitySumForLobal": 18, "commitRedundancyForLocal": false, "codeEntityRedundancyNumForGlobal": 8, "codeEntitySumForGlobal": 18, "commitRedundancyForGlobal": false}, "4dfa9995": {"codeEntityRedundancyNumForLocal": 4, "codeEntitySumForLobal": 6, "commitRedundancyForLocal": false, "codeEntityRedundancyNumForGlobal": 4, "codeEntitySumForGlobal": 6, "commitRedundancyForGlobal": false}, "08a2cc91": {"codeEntityRedundancyNumForLocal": 5, "codeEntitySumForLobal": 12, "commitRedundancyForLocal": false, "codeEntityRedundancyNumForGlobal": 5, "codeEntitySumForGlobal": 12, "commitRedundancyForGlobal": false}, "a6ba62b1": {"codeEntityRedundancyNumForLocal": 2, "codeEntitySumForLobal": 2, "commitRedundancyForLocal": true, "codeEntityRedundancyNumForGlobal": 2, "codeEntitySumForGlobal": 2, "commitRedundancyForGlobal": true}, "d830c29a": {"codeEntityRedundancyNumForLocal": 2, "codeEntitySumForLobal": 2, "commitRedundancyForLocal": true, "codeEntityRedundancyNumForGlobal": 2, "codeEntitySumForGlobal": 2, "commitRedundancyForGlobal": true}, "5e1e51d7": {"codeEntityRedundancyNumForLocal": 0, "codeEntitySumForLobal": 1, "commitRedundancyForLocal": false, "codeEntityRedundancyNumForGlobal": 0, "codeEntitySumForGlobal": 1, "commitRedundancyForGlobal": false}, "ad013adf": {"codeEntityRedundancyNumForLocal": 111, "codeEntitySumForLobal": 1504, "commitRedundancyForLocal": false, "codeEntityRedundancyNumForGlobal": 127, "codeEntitySumForGlobal": 1504, "commitRedundancyForGlobal": false}, "46d85f57": {"codeEntityRedundancyNumForLocal": 0, "codeEntitySumForLobal": 5, "commitRedundancyForLocal": false, "codeEntityRedundancyNumForGlobal": 0, "codeEntitySumForGlobal": 5, "commitRedundancyForGlobal": false}, "667cce62": {"codeEntityRedundancyNumForLocal": 61, "codeEntitySumForLobal": 73, "commitRedundancyForLocal": false, "codeEntityRedundancyNumForGlobal": 61, "codeEntitySumForGlobal": 73, "commitRedundancyForGlobal": false}, "7294cc36": {"codeEntityRedundancyNumForLocal": 1, "codeEntitySumForLobal": 23, "commitRedundancyForLocal": false, "codeEntityRedundancyNumForGlobal": 1, "codeEntitySumForGlobal": 23, "commitRedundancyForGlobal": false}, "d41d4106": {"codeEntityRedundancyNumForLocal": 4, "codeEntitySumForLobal": 4, "commitRedundancyForLocal": true, "codeEntityRedundancyNumForGlobal": 4, "codeEntitySumForGlobal": 4, "commitRedundancyForGlobal": true}, "52661138": {"codeEntityRedundancyNumForLocal": 1, "codeEntitySumForLobal": 1, "commitRedundancyForLocal": true, "codeEntityRedundancyNumForGlobal": 1, "codeEntitySumForGlobal": 1, "commitRedundancyForGlobal": true}, "95fd8168": {"codeEntityRedundancyNumForLocal": 98, "codeEntitySumForLobal": 107, "commitRedundancyForLocal": false, "codeEntityRedundancyNumForGlobal": 98, "codeEntitySumForGlobal": 107, "commitRedundancyForGlobal": false}, "f2fc5fc7": {"codeEntityRedundancyNumForLocal": 15, "codeEntitySumForLobal": 24, "commitRedundancyForLocal": false, "codeEntityRedundancyNumForGlobal": 15, "codeEntitySumForGlobal": 24, "commitRedundancyForGlobal": false}, "4c2a420f": {"codeEntityRedundancyNumForLocal": 2, "codeEntitySumForLobal": 3, "commitRedundancyForLocal": false, "codeEntityRedundancyNumForGlobal": 3, "codeEntitySumForGlobal": 3, "commitRedundancyForGlobal": true}, "f9de0eb7": {"codeEntityRedundancyNumForLocal": 0, "codeEntitySumForLobal": 0, "commitRedundancyForLocal": true, "codeEntityRedundancyNumForGlobal": 0, "codeEntitySumForGlobal": 0, "commitRedundancyForGlobal": true}, "d75b7766": {"codeEntityRedundancyNumForLocal": 24, "codeEntitySumForLobal": 44, "commitRedundancyForLocal": false, "codeEntityRedundancyNumForGlobal": 25, "codeEntitySumForGlobal": 44, "commitRedundancyForGlobal": false}, "e9bef11f": {"codeEntityRedundancyNumForLocal": 20, "codeEntitySumForLobal": 129, "commitRedundancyForLocal": false, "codeEntityRedundancyNumForGlobal": 25, "codeEntitySumForGlobal": 129, "commitRedundancyForGlobal": false}, "023e700e": {"codeEntityRedundancyNumForLocal": 5, "codeEntitySumForLobal": 15, "commitRedundancyForLocal": false, "codeEntityRedundancyNumForGlobal": 5, "codeEntitySumForGlobal": 15, "commitRedundancyForGlobal": false}, "8e452c33": {"codeEntityRedundancyNumForLocal": 19, "codeEntitySumForLobal": 31, "commitRedundancyForLocal": false, "codeEntityRedundancyNumForGlobal": 19, "codeEntitySumForGlobal": 31, "commitRedundancyForGlobal": false}, "eba3e9a0": {"codeEntityRedundancyNumForLocal": 1, "codeEntitySumForLobal": 2, "commitRedundancyForLocal": false, "codeEntityRedundancyNumForGlobal": 1, "codeEntitySumForGlobal": 2, "commitRedundancyForGlobal": false}, "e91424d4": {"codeEntityRedundancyNumForLocal": 1, "codeEntitySumForLobal": 2, "commitRedundancyForLocal": false, "codeEntityRedundancyNumForGlobal": 1, "codeEntitySumForGlobal": 2, "commitRedundancyForGlobal": false}, "4a1a3082": {"codeEntityRedundancyNumForLocal": 0, "codeEntitySumForLobal": 3, "commitRedundancyForLocal": false, "codeEntityRedundancyNumForGlobal": 0, "codeEntitySumForGlobal": 3, "commitRedundancyForGlobal": false}, "1f200f2d": {"codeEntityRedundancyNumForLocal": 0, "codeEntitySumForLobal": 0, "commitRedundancyForLocal": true, "codeEntityRedundancyNumForGlobal": 0, "codeEntitySumForGlobal": 0, "commitRedundancyForGlobal": true}, "529e49e0": {"codeEntityRedundancyNumForLocal": 0, "codeEntitySumForLobal": 0, "commitRedundancyForLocal": true, "codeEntityRedundancyNumForGlobal": 0, "codeEntitySumForGlobal": 0, "commitRedundancyForGlobal": true}, "ca2adcc9": {"codeEntityRedundancyNumForLocal": 0, "codeEntitySumForLobal": 0, "commitRedundancyForLocal": true, "codeEntityRedundancyNumForGlobal": 0, "codeEntitySumForGlobal": 0, "commitRedundancyForGlobal": true}, "6d2801f1": {"codeEntityRedundancyNumForLocal": 2, "codeEntitySumForLobal": 12, "commitRedundancyForLocal": false, "codeEntityRedundancyNumForGlobal": 2, "codeEntitySumForGlobal": 12, "commitRedundancyForGlobal": false}, "b322748e": {"codeEntityRedundancyNumForLocal": 3, "codeEntitySumForLobal": 10, "commitRedundancyForLocal": false, "codeEntityRedundancyNumForGlobal": 3, "codeEntitySumForGlobal": 10, "commitRedundancyForGlobal": false}, "cc445cdb": {"codeEntityRedundancyNumForLocal": 81, "codeEntitySumForLobal": 91, "commitRedundancyForLocal": false, "codeEntityRedundancyNumForGlobal": 81, "codeEntitySumForGlobal": 91, "commitRedundancyForGlobal": false}, "e1fb55bb": {"codeEntityRedundancyNumForLocal": 0, "codeEntitySumForLobal": 0, "commitRedundancyForLocal": true, "codeEntityRedundancyNumForGlobal": 0, "codeEntitySumForGlobal": 0, "commitRedundancyForGlobal": true}, "4afa53f4": {"codeEntityRedundancyNumForLocal": 23, "codeEntitySumForLobal": 32, "commitRedundancyForLocal": false, "codeEntityRedundancyNumForGlobal": 23, "codeEntitySumForGlobal": 32, "commitRedundancyForGlobal": false}, "52d60ba8": {"codeEntityRedundancyNumForLocal": 3, "codeEntitySumForLobal": 7, "commitRedundancyForLocal": false, "codeEntityRedundancyNumForGlobal": 3, "codeEntitySumForGlobal": 7, "commitRedundancyForGlobal": false}, "94267d5a": {"codeEntityRedundancyNumForLocal": 8, "codeEntitySumForLobal": 14, "commitRedundancyForLocal": false, "codeEntityRedundancyNumForGlobal": 8, "codeEntitySumForGlobal": 14, "commitRedundancyForGlobal": false}, "5c973105": {"codeEntityRedundancyNumForLocal": 511, "codeEntitySumForLobal": 536, "commitRedundancyForLocal": false, "codeEntityRedundancyNumForGlobal": 512, "codeEntitySumForGlobal": 536, "commitRedundancyForGlobal": false}, "3fcdeef9": {"codeEntityRedundancyNumForLocal": 2, "codeEntitySumForLobal": 31, "commitRedundancyForLocal": false, "codeEntityRedundancyNumForGlobal": 2, "codeEntitySumForGlobal": 31, "commitRedundancyForGlobal": false}, "6ddeb5a8": {"codeEntityRedundancyNumForLocal": 1, "codeEntitySumForLobal": 2, "commitRedundancyForLocal": false, "codeEntityRedundancyNumForGlobal": 2, "codeEntitySumForGlobal": 2, "commitRedundancyForGlobal": true}, "d8d19890": {"codeEntityRedundancyNumForLocal": 1, "codeEntitySumForLobal": 20, "commitRedundancyForLocal": false, "codeEntityRedundancyNumForGlobal": 1, "codeEntitySumForGlobal": 20, "commitRedundancyForGlobal": false}, "6d7d8d66": {"codeEntityRedundancyNumForLocal": 0, "codeEntitySumForLobal": 4, "commitRedundancyForLocal": false, "codeEntityRedundancyNumForGlobal": 0, "codeEntitySumForGlobal": 4, "commitRedundancyForGlobal": false}, "f46dbaef": {"codeEntityRedundancyNumForLocal": 25, "codeEntitySumForLobal": 31, "commitRedundancyForLocal": false, "codeEntityRedundancyNumForGlobal": 25, "codeEntitySumForGlobal": 31, "commitRedundancyForGlobal": false}, "a2e0793c": {"codeEntityRedundancyNumForLocal": 31, "codeEntitySumForLobal": 32, "commitRedundancyForLocal": false, "codeEntityRedundancyNumForGlobal": 31, "codeEntitySumForGlobal": 32, "commitRedundancyForGlobal": false}, "9b0409dc": {"codeEntityRedundancyNumForLocal": 0, "codeEntitySumForLobal": 0, "commitRedundancyForLocal": true, "codeEntityRedundancyNumForGlobal": 0, "codeEntitySumForGlobal": 0, "commitRedundancyForGlobal": true}, "3bfbbadb": {"codeEntityRedundancyNumForLocal": 8, "codeEntitySumForLobal": 8, "commitRedundancyForLocal": true, "codeEntityRedundancyNumForGlobal": 8, "codeEntitySumForGlobal": 8, "commitRedundancyForGlobal": true}, "32fa44c4": {"codeEntityRedundancyNumForLocal": 3, "codeEntitySumForLobal": 5, "commitRedundancyForLocal": false, "codeEntityRedundancyNumForGlobal": 3, "codeEntitySumForGlobal": 5, "commitRedundancyForGlobal": false}, "703f6cb4": {"codeEntityRedundancyNumForLocal": 2, "codeEntitySumForLobal": 2, "commitRedundancyForLocal": true, "codeEntityRedundancyNumForGlobal": 2, "codeEntitySumForGlobal": 2, "commitRedundancyForGlobal": true}, "f04f1e8c": {"codeEntityRedundancyNumForLocal": 0, "codeEntitySumForLobal": 8, "commitRedundancyForLocal": false, "codeEntityRedundancyNumForGlobal": 0, "codeEntitySumForGlobal": 8, "commitRedundancyForGlobal": false}, "eae1cabc": {"codeEntityRedundancyNumForLocal": 0, "codeEntitySumForLobal": 3, "commitRedundancyForLocal": false, "codeEntityRedundancyNumForGlobal": 0, "codeEntitySumForGlobal": 3, "commitRedundancyForGlobal": false}, "5e663053": {"codeEntityRedundancyNumForLocal": 7, "codeEntitySumForLobal": 32, "commitRedundancyForLocal": false, "codeEntityRedundancyNumForGlobal": 7, "codeEntitySumForGlobal": 32, "commitRedundancyForGlobal": false}, "a7973e98": {"codeEntityRedundancyNumForLocal": 0, "codeEntitySumForLobal": 0, "commitRedundancyForLocal": true, "codeEntityRedundancyNumForGlobal": 0, "codeEntitySumForGlobal": 0, "commitRedundancyForGlobal": true}, "080615c1": {"codeEntityRedundancyNumForLocal": 1, "codeEntitySumForLobal": 6, "commitRedundancyForLocal": false, "codeEntityRedundancyNumForGlobal": 1, "codeEntitySumForGlobal": 6, "commitRedundancyForGlobal": false}, "d45ac180": {"codeEntityRedundancyNumForLocal": 4, "codeEntitySumForLobal": 13, "commitRedundancyForLocal": false, "codeEntityRedundancyNumForGlobal": 5, "codeEntitySumForGlobal": 13, "commitRedundancyForGlobal": false}, "2bad1016": {"codeEntityRedundancyNumForLocal": 104, "codeEntitySumForLobal": 104, "commitRedundancyForLocal": true, "codeEntityRedundancyNumForGlobal": 104, "codeEntitySumForGlobal": 104, "commitRedundancyForGlobal": true}, "5ec9edd6": {"codeEntityRedundancyNumForLocal": 3, "codeEntitySumForLobal": 22, "commitRedundancyForLocal": false, "codeEntityRedundancyNumForGlobal": 3, "codeEntitySumForGlobal": 22, "commitRedundancyForGlobal": false}, "e6e3642c": {"codeEntityRedundancyNumForLocal": 0, "codeEntitySumForLobal": 4, "commitRedundancyForLocal": false, "codeEntityRedundancyNumForGlobal": 0, "codeEntitySumForGlobal": 4, "commitRedundancyForGlobal": false}, "79cff74d": {"codeEntityRedundancyNumForLocal": 1, "codeEntitySumForLobal": 34, "commitRedundancyForLocal": false, "codeEntityRedundancyNumForGlobal": 1, "codeEntitySumForGlobal": 34, "commitRedundancyForGlobal": false}, "863d5221": {"codeEntityRedundancyNumForLocal": 2, "codeEntitySumForLobal": 15, "commitRedundancyForLocal": false, "codeEntityRedundancyNumForGlobal": 3, "codeEntitySumForGlobal": 15, "commitRedundancyForGlobal": false}, "4c27cf80": {"codeEntityRedundancyNumForLocal": 4, "codeEntitySumForLobal": 36, "commitRedundancyForLocal": false, "codeEntityRedundancyNumForGlobal": 4, "codeEntitySumForGlobal": 36, "commitRedundancyForGlobal": false}, "2b0557b8": {"codeEntityRedundancyNumForLocal": 2, "codeEntitySumForLobal": 4, "commitRedundancyForLocal": false, "codeEntityRedundancyNumForGlobal": 2, "codeEntitySumForGlobal": 4, "commitRedundancyForGlobal": false}, "307aa9ec": {"codeEntityRedundancyNumForLocal": 114, "codeEntitySumForLobal": 147, "commitRedundancyForLocal": false, "codeEntityRedundancyNumForGlobal": 114, "codeEntitySumForGlobal": 147, "commitRedundancyForGlobal": false}, "5fb7e427": {"codeEntityRedundancyNumForLocal": 0, "codeEntitySumForLobal": 3, "commitRedundancyForLocal": false, "codeEntityRedundancyNumForGlobal": 2, "codeEntitySumForGlobal": 3, "commitRedundancyForGlobal": false}, "2661d846": {"codeEntityRedundancyNumForLocal": 30, "codeEntitySumForLobal": 30, "commitRedundancyForLocal": true, "codeEntityRedundancyNumForGlobal": 30, "codeEntitySumForGlobal": 30, "commitRedundancyForGlobal": true}, "84ea2c90": {"codeEntityRedundancyNumForLocal": 6, "codeEntitySumForLobal": 8, "commitRedundancyForLocal": false, "codeEntityRedundancyNumForGlobal": 6, "codeEntitySumForGlobal": 8, "commitRedundancyForGlobal": false}, "cbf7b36e": {"codeEntityRedundancyNumForLocal": 0, "codeEntitySumForLobal": 3, "commitRedundancyForLocal": false, "codeEntityRedundancyNumForGlobal": 0, "codeEntitySumForGlobal": 3, "commitRedundancyForGlobal": false}, "f066bb16": {"codeEntityRedundancyNumForLocal": 1, "codeEntitySumForLobal": 6, "commitRedundancyForLocal": false, "codeEntityRedundancyNumForGlobal": 1, "codeEntitySumForGlobal": 6, "commitRedundancyForGlobal": false}, "adb8f2ee": {"codeEntityRedundancyNumForLocal": 2, "codeEntitySumForLobal": 4, "commitRedundancyForLocal": false, "codeEntityRedundancyNumForGlobal": 2, "codeEntitySumForGlobal": 4, "commitRedundancyForGlobal": false}, "7d2ff677": {"codeEntityRedundancyNumForLocal": 0, "codeEntitySumForLobal": 0, "commitRedundancyForLocal": true, "codeEntityRedundancyNumForGlobal": 0, "codeEntitySumForGlobal": 0, "commitRedundancyForGlobal": true}, "59178b92": {"codeEntityRedundancyNumForLocal": 15, "codeEntitySumForLobal": 66, "commitRedundancyForLocal": false, "codeEntityRedundancyNumForGlobal": 15, "codeEntitySumForGlobal": 66, "commitRedundancyForGlobal": false}, "d243ab63": {"codeEntityRedundancyNumForLocal": 0, "codeEntitySumForLobal": 0, "commitRedundancyForLocal": true, "codeEntityRedundancyNumForGlobal": 0, "codeEntitySumForGlobal": 0, "commitRedundancyForGlobal": true}, "0c3be8c0": {"codeEntityRedundancyNumForLocal": 1, "codeEntitySumForLobal": 35, "commitRedundancyForLocal": false, "codeEntityRedundancyNumForGlobal": 1, "codeEntitySumForGlobal": 35, "commitRedundancyForGlobal": false}, "af8343d3": {"codeEntityRedundancyNumForLocal": 710, "codeEntitySumForLobal": 1889, "commitRedundancyForLocal": false, "codeEntityRedundancyNumForGlobal": 744, "codeEntitySumForGlobal": 1889, "commitRedundancyForGlobal": false}, "a4901b97": {"codeEntityRedundancyNumForLocal": 0, "codeEntitySumForLobal": 2, "commitRedundancyForLocal": false, "codeEntityRedundancyNumForGlobal": 0, "codeEntitySumForGlobal": 2, "commitRedundancyForGlobal": false}, "feee35ff": {"codeEntityRedundancyNumForLocal": 3, "codeEntitySumForLobal": 8, "commitRedundancyForLocal": false, "codeEntityRedundancyNumForGlobal": 3, "codeEntitySumForGlobal": 8, "commitRedundancyForGlobal": false}, "d663c0fe": {"codeEntityRedundancyNumForLocal": 2, "codeEntitySumForLobal": 2, "commitRedundancyForLocal": true, "codeEntityRedundancyNumForGlobal": 2, "codeEntitySumForGlobal": 2, "commitRedundancyForGlobal": true}, "53d6ccc8": {"codeEntityRedundancyNumForLocal": 1, "codeEntitySumForLobal": 1, "commitRedundancyForLocal": true, "codeEntityRedundancyNumForGlobal": 1, "codeEntitySumForGlobal": 1, "commitRedundancyForGlobal": true}, "5c462cc3": {"codeEntityRedundancyNumForLocal": 2, "codeEntitySumForLobal": 4, "commitRedundancyForLocal": false, "codeEntityRedundancyNumForGlobal": 2, "codeEntitySumForGlobal": 4, "commitRedundancyForGlobal": false}, "dde01442": {"codeEntityRedundancyNumForLocal": 21, "codeEntitySumForLobal": 61, "commitRedundancyForLocal": false, "codeEntityRedundancyNumForGlobal": 26, "codeEntitySumForGlobal": 61, "commitRedundancyForGlobal": false}, "da7e83d0": {"codeEntityRedundancyNumForLocal": 1, "codeEntitySumForLobal": 1, "commitRedundancyForLocal": true, "codeEntityRedundancyNumForGlobal": 1, "codeEntitySumForGlobal": 1, "commitRedundancyForGlobal": true}, "c7ab9adf": {"codeEntityRedundancyNumForLocal": 2, "codeEntitySumForLobal": 26, "commitRedundancyForLocal": false, "codeEntityRedundancyNumForGlobal": 2, "codeEntitySumForGlobal": 26, "commitRedundancyForGlobal": false}, "ea4193c6": {"codeEntityRedundancyNumForLocal": 14, "codeEntitySumForLobal": 24, "commitRedundancyForLocal": false, "codeEntityRedundancyNumForGlobal": 14, "codeEntitySumForGlobal": 24, "commitRedundancyForGlobal": false}, "53c9b142": {"codeEntityRedundancyNumForLocal": 0, "codeEntitySumForLobal": 2, "commitRedundancyForLocal": false, "codeEntityRedundancyNumForGlobal": 0, "codeEntitySumForGlobal": 2, "commitRedundancyForGlobal": false}, "1fb2d6b5": {"codeEntityRedundancyNumForLocal": 3, "codeEntitySumForLobal": 23, "commitRedundancyForLocal": false, "codeEntityRedundancyNumForGlobal": 3, "codeEntitySumForGlobal": 23, "commitRedundancyForGlobal": false}, "a8399260": {"codeEntityRedundancyNumForLocal": 0, "codeEntitySumForLobal": 0, "commitRedundancyForLocal": true, "codeEntityRedundancyNumForGlobal": 0, "codeEntitySumForGlobal": 0, "commitRedundancyForGlobal": true}, "b3ad452d": {"codeEntityRedundancyNumForLocal": 0, "codeEntitySumForLobal": 0, "commitRedundancyForLocal": true, "codeEntityRedundancyNumForGlobal": 0, "codeEntitySumForGlobal": 0, "commitRedundancyForGlobal": true}, "acc55e69": {"codeEntityRedundancyNumForLocal": 0, "codeEntitySumForLobal": 1, "commitRedundancyForLocal": false, "codeEntityRedundancyNumForGlobal": 0, "codeEntitySumForGlobal": 1, "commitRedundancyForGlobal": false}, "cdff214a": {"codeEntityRedundancyNumForLocal": 41, "codeEntitySumForLobal": 117, "commitRedundancyForLocal": false, "codeEntityRedundancyNumForGlobal": 47, "codeEntitySumForGlobal": 117, "commitRedundancyForGlobal": false}, "3da5ff50": {"codeEntityRedundancyNumForLocal": 17, "codeEntitySumForLobal": 36, "commitRedundancyForLocal": false, "codeEntityRedundancyNumForGlobal": 18, "codeEntitySumForGlobal": 36, "commitRedundancyForGlobal": false}, "ea30ee2a": {"codeEntityRedundancyNumForLocal": 6, "codeEntitySumForLobal": 24, "commitRedundancyForLocal": false, "codeEntityRedundancyNumForGlobal": 6, "codeEntitySumForGlobal": 24, "commitRedundancyForGlobal": false}, "95de42fc": {"codeEntityRedundancyNumForLocal": 0, "codeEntitySumForLobal": 0, "commitRedundancyForLocal": true, "codeEntityRedundancyNumForGlobal": 0, "codeEntitySumForGlobal": 0, "commitRedundancyForGlobal": true}, "fbe847ca": {"codeEntityRedundancyNumForLocal": 43, "codeEntitySumForLobal": 49, "commitRedundancyForLocal": false, "codeEntityRedundancyNumForGlobal": 43, "codeEntitySumForGlobal": 49, "commitRedundancyForGlobal": false}, "d7d8b4d9": {"codeEntityRedundancyNumForLocal": 9, "codeEntitySumForLobal": 12, "commitRedundancyForLocal": false, "codeEntityRedundancyNumForGlobal": 9, "codeEntitySumForGlobal": 12, "commitRedundancyForGlobal": false}, "fe130e23": {"codeEntityRedundancyNumForLocal": 14, "codeEntitySumForLobal": 38, "commitRedundancyForLocal": false, "codeEntityRedundancyNumForGlobal": 15, "codeEntitySumForGlobal": 38, "commitRedundancyForGlobal": false}, "d71b9ce5": {"codeEntityRedundancyNumForLocal": 2, "codeEntitySumForLobal": 6, "commitRedundancyForLocal": false, "codeEntityRedundancyNumForGlobal": 2, "codeEntitySumForGlobal": 6, "commitRedundancyForGlobal": false}, "00074fcc": {"codeEntityRedundancyNumForLocal": 0, "codeEntitySumForLobal": 1, "commitRedundancyForLocal": false, "codeEntityRedundancyNumForGlobal": 0, "codeEntitySumForGlobal": 1, "commitRedundancyForGlobal": false}, "ab9d13a4": {"codeEntityRedundancyNumForLocal": 3, "codeEntitySumForLobal": 12, "commitRedundancyForLocal": false, "codeEntityRedundancyNumForGlobal": 3, "codeEntitySumForGlobal": 12, "commitRedundancyForGlobal": false}, "65ad9465": {"codeEntityRedundancyNumForLocal": 0, "codeEntitySumForLobal": 0, "commitRedundancyForLocal": true, "codeEntityRedundancyNumForGlobal": 0, "codeEntitySumForGlobal": 0, "commitRedundancyForGlobal": true}, "30002b44": {"codeEntityRedundancyNumForLocal": 238, "codeEntitySumForLobal": 254, "commitRedundancyForLocal": false, "codeEntityRedundancyNumForGlobal": 238, "codeEntitySumForGlobal": 254, "commitRedundancyForGlobal": false}, "20edf83d": {"codeEntityRedundancyNumForLocal": 1, "codeEntitySumForLobal": 1, "commitRedundancyForLocal": true, "codeEntityRedundancyNumForGlobal": 1, "codeEntitySumForGlobal": 1, "commitRedundancyForGlobal": true}, "0a5bb35a": {"codeEntityRedundancyNumForLocal": 1, "codeEntitySumForLobal": 20, "commitRedundancyForLocal": false, "codeEntityRedundancyNumForGlobal": 2, "codeEntitySumForGlobal": 20, "commitRedundancyForGlobal": false}, "19ae9c4a": {"codeEntityRedundancyNumForLocal": 26, "codeEntitySumForLobal": 31, "commitRedundancyForLocal": false, "codeEntityRedundancyNumForGlobal": 26, "codeEntitySumForGlobal": 31, "commitRedundancyForGlobal": false}, "32ba6549": {"codeEntityRedundancyNumForLocal": 2, "codeEntitySumForLobal": 2, "commitRedundancyForLocal": true, "codeEntityRedundancyNumForGlobal": 2, "codeEntitySumForGlobal": 2, "commitRedundancyForGlobal": true}, "88365f90": {"codeEntityRedundancyNumForLocal": 2, "codeEntitySumForLobal": 2, "commitRedundancyForLocal": true, "codeEntityRedundancyNumForGlobal": 2, "codeEntitySumForGlobal": 2, "commitRedundancyForGlobal": true}, "3e70d3e5": {"codeEntityRedundancyNumForLocal": 0, "codeEntitySumForLobal": 10, "commitRedundancyForLocal": false, "codeEntityRedundancyNumForGlobal": 0, "codeEntitySumForGlobal": 10, "commitRedundancyForGlobal": false}, "668a9c91": {"codeEntityRedundancyNumForLocal": 0, "codeEntitySumForLobal": 0, "commitRedundancyForLocal": true, "codeEntityRedundancyNumForGlobal": 0, "codeEntitySumForGlobal": 0, "commitRedundancyForGlobal": true}, "50ee965b": {"codeEntityRedundancyNumForLocal": 2, "codeEntitySumForLobal": 12, "commitRedundancyForLocal": false, "codeEntityRedundancyNumForGlobal": 2, "codeEntitySumForGlobal": 12, "commitRedundancyForGlobal": false}, "f841deba": {"codeEntityRedundancyNumForLocal": 2, "codeEntitySumForLobal": 6, "commitRedundancyForLocal": false, "codeEntityRedundancyNumForGlobal": 2, "codeEntitySumForGlobal": 6, "commitRedundancyForGlobal": false}, "7e8495f8": {"codeEntityRedundancyNumForLocal": 0, "codeEntitySumForLobal": 2, "commitRedundancyForLocal": false, "codeEntityRedundancyNumForGlobal": 0, "codeEntitySumForGlobal": 2, "commitRedundancyForGlobal": false}, "7ce38e77": {"codeEntityRedundancyNumForLocal": 0, "codeEntitySumForLobal": 0, "commitRedundancyForLocal": true, "codeEntityRedundancyNumForGlobal": 0, "codeEntitySumForGlobal": 0, "commitRedundancyForGlobal": true}, "d89347ee": {"codeEntityRedundancyNumForLocal": 49, "codeEntitySumForLobal": 78, "commitRedundancyForLocal": false, "codeEntityRedundancyNumForGlobal": 63, "codeEntitySumForGlobal": 78, "commitRedundancyForGlobal": false}, "badee90e": {"codeEntityRedundancyNumForLocal": 0, "codeEntitySumForLobal": 2, "commitRedundancyForLocal": false, "codeEntityRedundancyNumForGlobal": 0, "codeEntitySumForGlobal": 2, "commitRedundancyForGlobal": false}, "2108fd4a": {"codeEntityRedundancyNumForLocal": 7, "codeEntitySumForLobal": 13, "commitRedundancyForLocal": false, "codeEntityRedundancyNumForGlobal": 7, "codeEntitySumForGlobal": 13, "commitRedundancyForGlobal": false}, "f19f0722": {"codeEntityRedundancyNumForLocal": 5, "codeEntitySumForLobal": 6, "commitRedundancyForLocal": false, "codeEntityRedundancyNumForGlobal": 5, "codeEntitySumForGlobal": 6, "commitRedundancyForGlobal": false}, "cc35a755": {"codeEntityRedundancyNumForLocal": 1, "codeEntitySumForLobal": 1, "commitRedundancyForLocal": true, "codeEntityRedundancyNumForGlobal": 1, "codeEntitySumForGlobal": 1, "commitRedundancyForGlobal": true}, "0db91db7": {"codeEntityRedundancyNumForLocal": 0, "codeEntitySumForLobal": 1, "commitRedundancyForLocal": false, "codeEntityRedundancyNumForGlobal": 0, "codeEntitySumForGlobal": 1, "commitRedundancyForGlobal": false}, "023558a9": {"codeEntityRedundancyNumForLocal": 4, "codeEntitySumForLobal": 16, "commitRedundancyForLocal": false, "codeEntityRedundancyNumForGlobal": 4, "codeEntitySumForGlobal": 16, "commitRedundancyForGlobal": false}, "5ae51ec2": {"codeEntityRedundancyNumForLocal": 0, "codeEntitySumForLobal": 0, "commitRedundancyForLocal": true, "codeEntityRedundancyNumForGlobal": 0, "codeEntitySumForGlobal": 0, "commitRedundancyForGlobal": true}, "748abbf0": {"codeEntityRedundancyNumForLocal": 41, "codeEntitySumForLobal": 364, "commitRedundancyForLocal": false, "codeEntityRedundancyNumForGlobal": 50, "codeEntitySumForGlobal": 364, "commitRedundancyForGlobal": false}, "efc02fc7": {"codeEntityRedundancyNumForLocal": 8, "codeEntitySumForLobal": 15, "commitRedundancyForLocal": false, "codeEntityRedundancyNumForGlobal": 8, "codeEntitySumForGlobal": 15, "commitRedundancyForGlobal": false}, "4dccc0cc": {"codeEntityRedundancyNumForLocal": 0, "codeEntitySumForLobal": 6, "commitRedundancyForLocal": false, "codeEntityRedundancyNumForGlobal": 0, "codeEntitySumForGlobal": 6, "commitRedundancyForGlobal": false}, "19037e55": {"codeEntityRedundancyNumForLocal": 1, "codeEntitySumForLobal": 1, "commitRedundancyForLocal": true, "codeEntityRedundancyNumForGlobal": 1, "codeEntitySumForGlobal": 1, "commitRedundancyForGlobal": true}, "0b5e6ef8": {"codeEntityRedundancyNumForLocal": 5, "codeEntitySumForLobal": 7, "commitRedundancyForLocal": false, "codeEntityRedundancyNumForGlobal": 5, "codeEntitySumForGlobal": 7, "commitRedundancyForGlobal": false}, "b30e1fa0": {"codeEntityRedundancyNumForLocal": 0, "codeEntitySumForLobal": 0, "commitRedundancyForLocal": true, "codeEntityRedundancyNumForGlobal": 0, "codeEntitySumForGlobal": 0, "commitRedundancyForGlobal": true}, "6ae2719a": {"codeEntityRedundancyNumForLocal": 0, "codeEntitySumForLobal": 0, "commitRedundancyForLocal": true, "codeEntityRedundancyNumForGlobal": 0, "codeEntitySumForGlobal": 0, "commitRedundancyForGlobal": true}, "b07b7146": {"codeEntityRedundancyNumForLocal": 13, "codeEntitySumForLobal": 19, "commitRedundancyForLocal": false, "codeEntityRedundancyNumForGlobal": 13, "codeEntitySumForGlobal": 19, "commitRedundancyForGlobal": false}, "a3256c4d": {"codeEntityRedundancyNumForLocal": 5, "codeEntitySumForLobal": 6, "commitRedundancyForLocal": false, "codeEntityRedundancyNumForGlobal": 5, "codeEntitySumForGlobal": 6, "commitRedundancyForGlobal": false}, "b6384e41": {"codeEntityRedundancyNumForLocal": 0, "codeEntitySumForLobal": 2, "commitRedundancyForLocal": false, "codeEntityRedundancyNumForGlobal": 0, "codeEntitySumForGlobal": 2, "commitRedundancyForGlobal": false}, "d9616de4": {"codeEntityRedundancyNumForLocal": 0, "codeEntitySumForLobal": 0, "commitRedundancyForLocal": true, "codeEntityRedundancyNumForGlobal": 0, "codeEntitySumForGlobal": 0, "commitRedundancyForGlobal": true}, "d6673e12": {"codeEntityRedundancyNumForLocal": 5, "codeEntitySumForLobal": 20, "commitRedundancyForLocal": false, "codeEntityRedundancyNumForGlobal": 7, "codeEntitySumForGlobal": 20, "commitRedundancyForGlobal": false}, "b24b1029": {"codeEntityRedundancyNumForLocal": 73, "codeEntitySumForLobal": 73, "commitRedundancyForLocal": true, "codeEntityRedundancyNumForGlobal": 73, "codeEntitySumForGlobal": 73, "commitRedundancyForGlobal": true}, "de2a9e0c": {"codeEntityRedundancyNumForLocal": 229, "codeEntitySumForLobal": 243, "commitRedundancyForLocal": false, "codeEntityRedundancyNumForGlobal": 229, "codeEntitySumForGlobal": 243, "commitRedundancyForGlobal": false}, "ddad06a4": {"codeEntityRedundancyNumForLocal": 3, "codeEntitySumForLobal": 4, "commitRedundancyForLocal": false, "codeEntityRedundancyNumForGlobal": 3, "codeEntitySumForGlobal": 4, "commitRedundancyForGlobal": false}, "5d3b6b7c": {"codeEntityRedundancyNumForLocal": 8, "codeEntitySumForLobal": 34, "commitRedundancyForLocal": false, "codeEntityRedundancyNumForGlobal": 10, "codeEntitySumForGlobal": 34, "commitRedundancyForGlobal": false}, "8fe52f9c": {"codeEntityRedundancyNumForLocal": 29, "codeEntitySumForLobal": 49, "commitRedundancyForLocal": false, "codeEntityRedundancyNumForGlobal": 29, "codeEntitySumForGlobal": 49, "commitRedundancyForGlobal": false}, "928932c6": {"codeEntityRedundancyNumForLocal": 0, "codeEntitySumForLobal": 2, "commitRedundancyForLocal": false, "codeEntityRedundancyNumForGlobal": 0, "codeEntitySumForGlobal": 2, "commitRedundancyForGlobal": false}, "6ac4a06d": {"codeEntityRedundancyNumForLocal": 0, "codeEntitySumForLobal": 0, "commitRedundancyForLocal": true, "codeEntityRedundancyNumForGlobal": 0, "codeEntitySumForGlobal": 0, "commitRedundancyForGlobal": true}, "422648e2": {"codeEntityRedundancyNumForLocal": 23, "codeEntitySumForLobal": 39, "commitRedundancyForLocal": false, "codeEntityRedundancyNumForGlobal": 23, "codeEntitySumForGlobal": 39, "commitRedundancyForGlobal": false}, "2b4e6101": {"codeEntityRedundancyNumForLocal": 117, "codeEntitySumForLobal": 153, "commitRedundancyForLocal": false, "codeEntityRedundancyNumForGlobal": 117, "codeEntitySumForGlobal": 153, "commitRedundancyForGlobal": false}, "a4e49732": {"codeEntityRedundancyNumForLocal": 0, "codeEntitySumForLobal": 0, "commitRedundancyForLocal": true, "codeEntityRedundancyNumForGlobal": 0, "codeEntitySumForGlobal": 0, "commitRedundancyForGlobal": true}, "a0ee3d4e": {"codeEntityRedundancyNumForLocal": 2, "codeEntitySumForLobal": 2, "commitRedundancyForLocal": true, "codeEntityRedundancyNumForGlobal": 2, "codeEntitySumForGlobal": 2, "commitRedundancyForGlobal": true}, "2085fb1b": {"codeEntityRedundancyNumForLocal": 1, "codeEntitySumForLobal": 1, "commitRedundancyForLocal": true, "codeEntityRedundancyNumForGlobal": 1, "codeEntitySumForGlobal": 1, "commitRedundancyForGlobal": true}, "872e9a59": {"codeEntityRedundancyNumForLocal": 3, "codeEntitySumForLobal": 4, "commitRedundancyForLocal": false, "codeEntityRedundancyNumForGlobal": 3, "codeEntitySumForGlobal": 4, "commitRedundancyForGlobal": false}, "67570100": {"codeEntityRedundancyNumForLocal": 3, "codeEntitySumForLobal": 3, "commitRedundancyForLocal": true, "codeEntityRedundancyNumForGlobal": 3, "codeEntitySumForGlobal": 3, "commitRedundancyForGlobal": true}, "aa28fac1": {"codeEntityRedundancyNumForLocal": 4, "codeEntitySumForLobal": 5, "commitRedundancyForLocal": false, "codeEntityRedundancyNumForGlobal": 4, "codeEntitySumForGlobal": 5, "commitRedundancyForGlobal": false}, "e9aecdfd": {"codeEntityRedundancyNumForLocal": 2, "codeEntitySumForLobal": 5, "commitRedundancyForLocal": false, "codeEntityRedundancyNumForGlobal": 2, "codeEntitySumForGlobal": 5, "commitRedundancyForGlobal": false}, "78d6e2c7": {"codeEntityRedundancyNumForLocal": 0, "codeEntitySumForLobal": 0, "commitRedundancyForLocal": true, "codeEntityRedundancyNumForGlobal": 0, "codeEntitySumForGlobal": 0, "commitRedundancyForGlobal": true}, "769e00cc": {"codeEntityRedundancyNumForLocal": 12, "codeEntitySumForLobal": 29, "commitRedundancyForLocal": false, "codeEntityRedundancyNumForGlobal": 12, "codeEntitySumForGlobal": 29, "commitRedundancyForGlobal": false}, "c2116672": {"codeEntityRedundancyNumForLocal": 0, "codeEntitySumForLobal": 4, "commitRedundancyForLocal": false, "codeEntityRedundancyNumForGlobal": 1, "codeEntitySumForGlobal": 4, "commitRedundancyForGlobal": false}, "6c759785": {"codeEntityRedundancyNumForLocal": 10, "codeEntitySumForLobal": 21, "commitRedundancyForLocal": false, "codeEntityRedundancyNumForGlobal": 10, "codeEntitySumForGlobal": 21, "commitRedundancyForGlobal": false}, "1cbbcfb9": {"codeEntityRedundancyNumForLocal": 0, "codeEntitySumForLobal": 4, "commitRedundancyForLocal": false, "codeEntityRedundancyNumForGlobal": 0, "codeEntitySumForGlobal": 4, "commitRedundancyForGlobal": false}, "d7ca271d": {"codeEntityRedundancyNumForLocal": 31, "codeEntitySumForLobal": 34, "commitRedundancyForLocal": false, "codeEntityRedundancyNumForGlobal": 31, "codeEntitySumForGlobal": 34, "commitRedundancyForGlobal": false}, "f38e5fd1": {"codeEntityRedundancyNumForLocal": 0, "codeEntitySumForLobal": 0, "commitRedundancyForLocal": true, "codeEntityRedundancyNumForGlobal": 0, "codeEntitySumForGlobal": 0, "commitRedundancyForGlobal": true}, "89fbbd1b": {"codeEntityRedundancyNumForLocal": 0, "codeEntitySumForLobal": 1, "commitRedundancyForLocal": false, "codeEntityRedundancyNumForGlobal": 0, "codeEntitySumForGlobal": 1, "commitRedundancyForGlobal": false}, "3335dbcf": {"codeEntityRedundancyNumForLocal": 17, "codeEntitySumForLobal": 63, "commitRedundancyForLocal": false, "codeEntityRedundancyNumForGlobal": 17, "codeEntitySumForGlobal": 63, "commitRedundancyForGlobal": false}, "70f58125": {"codeEntityRedundancyNumForLocal": 9, "codeEntitySumForLobal": 9, "commitRedundancyForLocal": true, "codeEntityRedundancyNumForGlobal": 9, "codeEntitySumForGlobal": 9, "commitRedundancyForGlobal": true}, "6f9a7228": {"codeEntityRedundancyNumForLocal": 12, "codeEntitySumForLobal": 37, "commitRedundancyForLocal": false, "codeEntityRedundancyNumForGlobal": 12, "codeEntitySumForGlobal": 37, "commitRedundancyForGlobal": false}, "d7cb64eb": {"codeEntityRedundancyNumForLocal": 18, "codeEntitySumForLobal": 21, "commitRedundancyForLocal": false, "codeEntityRedundancyNumForGlobal": 18, "codeEntitySumForGlobal": 21, "commitRedundancyForGlobal": false}, "bcfa13de": {"codeEntityRedundancyNumForLocal": 0, "codeEntitySumForLobal": 1, "commitRedundancyForLocal": false, "codeEntityRedundancyNumForGlobal": 0, "codeEntitySumForGlobal": 1, "commitRedundancyForGlobal": false}, "5ec45f38": {"codeEntityRedundancyNumForLocal": 4, "codeEntitySumForLobal": 11, "commitRedundancyForLocal": false, "codeEntityRedundancyNumForGlobal": 4, "codeEntitySumForGlobal": 11, "commitRedundancyForGlobal": false}, "b80a7aef": {"codeEntityRedundancyNumForLocal": 5, "codeEntitySumForLobal": 15, "commitRedundancyForLocal": false, "codeEntityRedundancyNumForGlobal": 6, "codeEntitySumForGlobal": 15, "commitRedundancyForGlobal": false}, "9d1acd71": {"codeEntityRedundancyNumForLocal": 0, "codeEntitySumForLobal": 1, "commitRedundancyForLocal": false, "codeEntityRedundancyNumForGlobal": 0, "codeEntitySumForGlobal": 1, "commitRedundancyForGlobal": false}, "9ab1bf5e": {"codeEntityRedundancyNumForLocal": 0, "codeEntitySumForLobal": 3, "commitRedundancyForLocal": false, "codeEntityRedundancyNumForGlobal": 0, "codeEntitySumForGlobal": 3, "commitRedundancyForGlobal": false}, "388f59e2": {"codeEntityRedundancyNumForLocal": 2, "codeEntitySumForLobal": 2, "commitRedundancyForLocal": true, "codeEntityRedundancyNumForGlobal": 2, "codeEntitySumForGlobal": 2, "commitRedundancyForGlobal": true}, "a0597730": {"codeEntityRedundancyNumForLocal": 0, "codeEntitySumForLobal": 0, "commitRedundancyForLocal": true, "codeEntityRedundancyNumForGlobal": 0, "codeEntitySumForGlobal": 0, "commitRedundancyForGlobal": true}, "edf229b9": {"codeEntityRedundancyNumForLocal": 8, "codeEntitySumForLobal": 15, "commitRedundancyForLocal": false, "codeEntityRedundancyNumForGlobal": 8, "codeEntitySumForGlobal": 15, "commitRedundancyForGlobal": false}, "d7f35e5a": {"codeEntityRedundancyNumForLocal": 2, "codeEntitySumForLobal": 4, "commitRedundancyForLocal": false, "codeEntityRedundancyNumForGlobal": 2, "codeEntitySumForGlobal": 4, "commitRedundancyForGlobal": false}, "0e45d6d8": {"codeEntityRedundancyNumForLocal": 24, "codeEntitySumForLobal": 36, "commitRedundancyForLocal": false, "codeEntityRedundancyNumForGlobal": 24, "codeEntitySumForGlobal": 36, "commitRedundancyForGlobal": false}, "a4201a73": {"codeEntityRedundancyNumForLocal": 0, "codeEntitySumForLobal": 0, "commitRedundancyForLocal": true, "codeEntityRedundancyNumForGlobal": 0, "codeEntitySumForGlobal": 0, "commitRedundancyForGlobal": true}, "b5fc7551": {"codeEntityRedundancyNumForLocal": 0, "codeEntitySumForLobal": 0, "commitRedundancyForLocal": true, "codeEntityRedundancyNumForGlobal": 0, "codeEntitySumForGlobal": 0, "commitRedundancyForGlobal": true}, "4e15e0a7": {"codeEntityRedundancyNumForLocal": 0, "codeEntitySumForLobal": 3, "commitRedundancyForLocal": false, "codeEntityRedundancyNumForGlobal": 0, "codeEntitySumForGlobal": 3, "commitRedundancyForGlobal": false}, "7c5dff2c": {"codeEntityRedundancyNumForLocal": 1, "codeEntitySumForLobal": 9, "commitRedundancyForLocal": false, "codeEntityRedundancyNumForGlobal": 1, "codeEntitySumForGlobal": 9, "commitRedundancyForGlobal": false}, "efba8a49": {"codeEntityRedundancyNumForLocal": 0, "codeEntitySumForLobal": 0, "commitRedundancyForLocal": true, "codeEntityRedundancyNumForGlobal": 0, "codeEntitySumForGlobal": 0, "commitRedundancyForGlobal": true}, "6ed1fc22": {"codeEntityRedundancyNumForLocal": 46, "codeEntitySumForLobal": 52, "commitRedundancyForLocal": false, "codeEntityRedundancyNumForGlobal": 46, "codeEntitySumForGlobal": 52, "commitRedundancyForGlobal": false}, "d052aa89": {"codeEntityRedundancyNumForLocal": 1, "codeEntitySumForLobal": 1, "commitRedundancyForLocal": true, "codeEntityRedundancyNumForGlobal": 1, "codeEntitySumForGlobal": 1, "commitRedundancyForGlobal": true}, "6fadc441": {"codeEntityRedundancyNumForLocal": 95, "codeEntitySumForLobal": 112, "commitRedundancyForLocal": false, "codeEntityRedundancyNumForGlobal": 95, "codeEntitySumForGlobal": 112, "commitRedundancyForGlobal": false}, "4df86257": {"codeEntityRedundancyNumForLocal": 2, "codeEntitySumForLobal": 6, "commitRedundancyForLocal": false, "codeEntityRedundancyNumForGlobal": 2, "codeEntitySumForGlobal": 6, "commitRedundancyForGlobal": false}, "53da0833": {"codeEntityRedundancyNumForLocal": 6, "codeEntitySumForLobal": 64, "commitRedundancyForLocal": false, "codeEntityRedundancyNumForGlobal": 6, "codeEntitySumForGlobal": 64, "commitRedundancyForGlobal": false}, "c8b35386": {"codeEntityRedundancyNumForLocal": 799, "codeEntitySumForLobal": 2604, "commitRedundancyForLocal": false, "codeEntityRedundancyNumForGlobal": 799, "codeEntitySumForGlobal": 2604, "commitRedundancyForGlobal": false}, "e003339d": {"codeEntityRedundancyNumForLocal": 4, "codeEntitySumForLobal": 16, "commitRedundancyForLocal": false, "codeEntityRedundancyNumForGlobal": 4, "codeEntitySumForGlobal": 16, "commitRedundancyForGlobal": false}, "6130461e": {"codeEntityRedundancyNumForLocal": 6, "codeEntitySumForLobal": 15, "commitRedundancyForLocal": false, "codeEntityRedundancyNumForGlobal": 6, "codeEntitySumForGlobal": 15, "commitRedundancyForGlobal": false}, "2e95ab2f": {"codeEntityRedundancyNumForLocal": 10, "codeEntitySumForLobal": 106, "commitRedundancyForLocal": false, "codeEntityRedundancyNumForGlobal": 10, "codeEntitySumForGlobal": 106, "commitRedundancyForGlobal": false}, "2383608d": {"codeEntityRedundancyNumForLocal": 2, "codeEntitySumForLobal": 3, "commitRedundancyForLocal": false, "codeEntityRedundancyNumForGlobal": 2, "codeEntitySumForGlobal": 3, "commitRedundancyForGlobal": false}, "7b07569d": {"codeEntityRedundancyNumForLocal": 11, "codeEntitySumForLobal": 45, "commitRedundancyForLocal": false, "codeEntityRedundancyNumForGlobal": 11, "codeEntitySumForGlobal": 45, "commitRedundancyForGlobal": false}, "b89a22a9": {"codeEntityRedundancyNumForLocal": 81, "codeEntitySumForLobal": 81, "commitRedundancyForLocal": true, "codeEntityRedundancyNumForGlobal": 81, "codeEntitySumForGlobal": 81, "commitRedundancyForGlobal": true}, "f2f0a9d2": {"codeEntityRedundancyNumForLocal": 2, "codeEntitySumForLobal": 4, "commitRedundancyForLocal": false, "codeEntityRedundancyNumForGlobal": 2, "codeEntitySumForGlobal": 4, "commitRedundancyForGlobal": false}, "7a0fe7af": {"codeEntityRedundancyNumForLocal": 2, "codeEntitySumForLobal": 18, "commitRedundancyForLocal": false, "codeEntityRedundancyNumForGlobal": 2, "codeEntitySumForGlobal": 18, "commitRedundancyForGlobal": false}, "371a211b": {"codeEntityRedundancyNumForLocal": 0, "codeEntitySumForLobal": 2, "commitRedundancyForLocal": false, "codeEntityRedundancyNumForGlobal": 0, "codeEntitySumForGlobal": 2, "commitRedundancyForGlobal": false}, "9bde93c9": {"codeEntityRedundancyNumForLocal": 1, "codeEntitySumForLobal": 1, "commitRedundancyForLocal": true, "codeEntityRedundancyNumForGlobal": 1, "codeEntitySumForGlobal": 1, "commitRedundancyForGlobal": true}, "287f9d81": {"codeEntityRedundancyNumForLocal": 0, "codeEntitySumForLobal": 8, "commitRedundancyForLocal": false, "codeEntityRedundancyNumForGlobal": 0, "codeEntitySumForGlobal": 8, "commitRedundancyForGlobal": false}, "6a213fbe": {"codeEntityRedundancyNumForLocal": 0, "codeEntitySumForLobal": 1, "commitRedundancyForLocal": false, "codeEntityRedundancyNumForGlobal": 0, "codeEntitySumForGlobal": 1, "commitRedundancyForGlobal": false}, "46895051": {"codeEntityRedundancyNumForLocal": 0, "codeEntitySumForLobal": 6, "commitRedundancyForLocal": false, "codeEntityRedundancyNumForGlobal": 0, "codeEntitySumForGlobal": 6, "commitRedundancyForGlobal": false}, "47df2f38": {"codeEntityRedundancyNumForLocal": 1, "codeEntitySumForLobal": 1, "commitRedundancyForLocal": true, "codeEntityRedundancyNumForGlobal": 1, "codeEntitySumForGlobal": 1, "commitRedundancyForGlobal": true}, "cfc3d478": {"codeEntityRedundancyNumForLocal": 3, "codeEntitySumForLobal": 4, "commitRedundancyForLocal": false, "codeEntityRedundancyNumForGlobal": 3, "codeEntitySumForGlobal": 4, "commitRedundancyForGlobal": false}, "8fa0146c": {"codeEntityRedundancyNumForLocal": 0, "codeEntitySumForLobal": 3, "commitRedundancyForLocal": false, "codeEntityRedundancyNumForGlobal": 0, "codeEntitySumForGlobal": 3, "commitRedundancyForGlobal": false}, "58d07847": {"codeEntityRedundancyNumForLocal": 3, "codeEntitySumForLobal": 14, "commitRedundancyForLocal": false, "codeEntityRedundancyNumForGlobal": 3, "codeEntitySumForGlobal": 14, "commitRedundancyForGlobal": false}, "d8f029d4": {"codeEntityRedundancyNumForLocal": 1, "codeEntitySumForLobal": 1, "commitRedundancyForLocal": true, "codeEntityRedundancyNumForGlobal": 1, "codeEntitySumForGlobal": 1, "commitRedundancyForGlobal": true}, "2d48fb36": {"codeEntityRedundancyNumForLocal": 0, "codeEntitySumForLobal": 5, "commitRedundancyForLocal": false, "codeEntityRedundancyNumForGlobal": 0, "codeEntitySumForGlobal": 5, "commitRedundancyForGlobal": false}, "7f10f5cd": {"codeEntityRedundancyNumForLocal": 0, "codeEntitySumForLobal": 0, "commitRedundancyForLocal": true, "codeEntityRedundancyNumForGlobal": 0, "codeEntitySumForGlobal": 0, "commitRedundancyForGlobal": true}, "1807d51e": {"codeEntityRedundancyNumForLocal": 0, "codeEntitySumForLobal": 17, "commitRedundancyForLocal": false, "codeEntityRedundancyNumForGlobal": 0, "codeEntitySumForGlobal": 17, "commitRedundancyForGlobal": false}, "8d1dce02": {"codeEntityRedundancyNumForLocal": 6, "codeEntitySumForLobal": 6, "commitRedundancyForLocal": true, "codeEntityRedundancyNumForGlobal": 6, "codeEntitySumForGlobal": 6, "commitRedundancyForGlobal": true}, "17597686": {"codeEntityRedundancyNumForLocal": 1, "codeEntitySumForLobal": 10, "commitRedundancyForLocal": false, "codeEntityRedundancyNumForGlobal": 1, "codeEntitySumForGlobal": 10, "commitRedundancyForGlobal": false}, "3359d61d": {"codeEntityRedundancyNumForLocal": 0, "codeEntitySumForLobal": 1, "commitRedundancyForLocal": false, "codeEntityRedundancyNumForGlobal": 0, "codeEntitySumForGlobal": 1, "commitRedundancyForGlobal": false}, "bec6c9e7": {"codeEntityRedundancyNumForLocal": 261, "codeEntitySumForLobal": 282, "commitRedundancyForLocal": false, "codeEntityRedundancyNumForGlobal": 261, "codeEntitySumForGlobal": 282, "commitRedundancyForGlobal": false}, "994389fe": {"codeEntityRedundancyNumForLocal": 3, "codeEntitySumForLobal": 11, "commitRedundancyForLocal": false, "codeEntityRedundancyNumForGlobal": 3, "codeEntitySumForGlobal": 11, "commitRedundancyForGlobal": false}, "6dd65c2e": {"codeEntityRedundancyNumForLocal": 2, "codeEntitySumForLobal": 15, "commitRedundancyForLocal": false, "codeEntityRedundancyNumForGlobal": 2, "codeEntitySumForGlobal": 15, "commitRedundancyForGlobal": false}, "075fddd5": {"codeEntityRedundancyNumForLocal": 0, "codeEntitySumForLobal": 0, "commitRedundancyForLocal": true, "codeEntityRedundancyNumForGlobal": 0, "codeEntitySumForGlobal": 0, "commitRedundancyForGlobal": true}, "eb07d277": {"codeEntityRedundancyNumForLocal": 1, "codeEntitySumForLobal": 4, "commitRedundancyForLocal": false, "codeEntityRedundancyNumForGlobal": 1, "codeEntitySumForGlobal": 4, "commitRedundancyForGlobal": false}, "d805b5ad": {"codeEntityRedundancyNumForLocal": 7, "codeEntitySumForLobal": 35, "commitRedundancyForLocal": false, "codeEntityRedundancyNumForGlobal": 7, "codeEntitySumForGlobal": 35, "commitRedundancyForGlobal": false}, "9c5fa368": {"codeEntityRedundancyNumForLocal": 9, "codeEntitySumForLobal": 9, "commitRedundancyForLocal": true, "codeEntityRedundancyNumForGlobal": 9, "codeEntitySumForGlobal": 9, "commitRedundancyForGlobal": true}, "8eec2b45": {"codeEntityRedundancyNumForLocal": 3, "codeEntitySumForLobal": 4, "commitRedundancyForLocal": false, "codeEntityRedundancyNumForGlobal": 3, "codeEntitySumForGlobal": 4, "commitRedundancyForGlobal": false}, "c2ec68ce": {"codeEntityRedundancyNumForLocal": 8, "codeEntitySumForLobal": 10, "commitRedundancyForLocal": false, "codeEntityRedundancyNumForGlobal": 8, "codeEntitySumForGlobal": 10, "commitRedundancyForGlobal": false}, "2a8e0bb9": {"codeEntityRedundancyNumForLocal": 1, "codeEntitySumForLobal": 3, "commitRedundancyForLocal": false, "codeEntityRedundancyNumForGlobal": 1, "codeEntitySumForGlobal": 3, "commitRedundancyForGlobal": false}, "62073bb3": {"codeEntityRedundancyNumForLocal": 1, "codeEntitySumForLobal": 1, "commitRedundancyForLocal": true, "codeEntityRedundancyNumForGlobal": 1, "codeEntitySumForGlobal": 1, "commitRedundancyForGlobal": true}, "861c05ec": {"codeEntityRedundancyNumForLocal": 5, "codeEntitySumForLobal": 15, "commitRedundancyForLocal": false, "codeEntityRedundancyNumForGlobal": 6, "codeEntitySumForGlobal": 15, "commitRedundancyForGlobal": false}, "d4b38e58": {"codeEntityRedundancyNumForLocal": 9, "codeEntitySumForLobal": 75, "commitRedundancyForLocal": false, "codeEntityRedundancyNumForGlobal": 9, "codeEntitySumForGlobal": 75, "commitRedundancyForGlobal": false}, "0572ba6a": {"codeEntityRedundancyNumForLocal": 0, "codeEntitySumForLobal": 4, "commitRedundancyForLocal": false, "codeEntityRedundancyNumForGlobal": 0, "codeEntitySumForGlobal": 4, "commitRedundancyForGlobal": false}, "300762ac": {"codeEntityRedundancyNumForLocal": 0, "codeEntitySumForLobal": 2, "commitRedundancyForLocal": false, "codeEntityRedundancyNumForGlobal": 0, "codeEntitySumForGlobal": 2, "commitRedundancyForGlobal": false}, "bfbe668b": {"codeEntityRedundancyNumForLocal": 0, "codeEntitySumForLobal": 0, "commitRedundancyForLocal": true, "codeEntityRedundancyNumForGlobal": 0, "codeEntitySumForGlobal": 0, "commitRedundancyForGlobal": true}, "729ad636": {"codeEntityRedundancyNumForLocal": 0, "codeEntitySumForLobal": 1, "commitRedundancyForLocal": false, "codeEntityRedundancyNumForGlobal": 0, "codeEntitySumForGlobal": 1, "commitRedundancyForGlobal": false}, "04342240": {"codeEntityRedundancyNumForLocal": 0, "codeEntitySumForLobal": 3, "commitRedundancyForLocal": false, "codeEntityRedundancyNumForGlobal": 0, "codeEntitySumForGlobal": 3, "commitRedundancyForGlobal": false}, "bf9d1010": {"codeEntityRedundancyNumForLocal": 1, "codeEntitySumForLobal": 3, "commitRedundancyForLocal": false, "codeEntityRedundancyNumForGlobal": 1, "codeEntitySumForGlobal": 3, "commitRedundancyForGlobal": false}, "9bd8f962": {"codeEntityRedundancyNumForLocal": 3, "codeEntitySumForLobal": 6, "commitRedundancyForLocal": false, "codeEntityRedundancyNumForGlobal": 3, "codeEntitySumForGlobal": 6, "commitRedundancyForGlobal": false}, "ae68624b": {"codeEntityRedundancyNumForLocal": 0, "codeEntitySumForLobal": 0, "commitRedundancyForLocal": true, "codeEntityRedundancyNumForGlobal": 0, "codeEntitySumForGlobal": 0, "commitRedundancyForGlobal": true}, "9858198e": {"codeEntityRedundancyNumForLocal": 60, "codeEntitySumForLobal": 66, "commitRedundancyForLocal": false, "codeEntityRedundancyNumForGlobal": 60, "codeEntitySumForGlobal": 66, "commitRedundancyForGlobal": false}, "8e17b350": {"codeEntityRedundancyNumForLocal": 0, "codeEntitySumForLobal": 2, "commitRedundancyForLocal": false, "codeEntityRedundancyNumForGlobal": 0, "codeEntitySumForGlobal": 2, "commitRedundancyForGlobal": false}, "eac9ac5c": {"codeEntityRedundancyNumForLocal": 0, "codeEntitySumForLobal": 0, "commitRedundancyForLocal": true, "codeEntityRedundancyNumForGlobal": 0, "codeEntitySumForGlobal": 0, "commitRedundancyForGlobal": true}, "46406e77": {"codeEntityRedundancyNumForLocal": 0, "codeEntitySumForLobal": 3, "commitRedundancyForLocal": false, "codeEntityRedundancyNumForGlobal": 0, "codeEntitySumForGlobal": 3, "commitRedundancyForGlobal": false}, "badecc1e": {"codeEntityRedundancyNumForLocal": 0, "codeEntitySumForLobal": 8, "commitRedundancyForLocal": false, "codeEntityRedundancyNumForGlobal": 0, "codeEntitySumForGlobal": 8, "commitRedundancyForGlobal": false}, "2dc620cb": {"codeEntityRedundancyNumForLocal": 0, "codeEntitySumForLobal": 2, "commitRedundancyForLocal": false, "codeEntityRedundancyNumForGlobal": 0, "codeEntitySumForGlobal": 2, "commitRedundancyForGlobal": false}, "7ba6868f": {"codeEntityRedundancyNumForLocal": 0, "codeEntitySumForLobal": 0, "commitRedundancyForLocal": true, "codeEntityRedundancyNumForGlobal": 0, "codeEntitySumForGlobal": 0, "commitRedundancyForGlobal": true}, "0dccc0f6": {"codeEntityRedundancyNumForLocal": 1, "codeEntitySumForLobal": 14, "commitRedundancyForLocal": false, "codeEntityRedundancyNumForGlobal": 3, "codeEntitySumForGlobal": 14, "commitRedundancyForGlobal": false}, "fe66c92e": {"codeEntityRedundancyNumForLocal": 16, "codeEntitySumForLobal": 51, "commitRedundancyForLocal": false, "codeEntityRedundancyNumForGlobal": 16, "codeEntitySumForGlobal": 51, "commitRedundancyForGlobal": false}, "0b4d9a7e": {"codeEntityRedundancyNumForLocal": 16, "codeEntitySumForLobal": 16, "commitRedundancyForLocal": true, "codeEntityRedundancyNumForGlobal": 16, "codeEntitySumForGlobal": 16, "commitRedundancyForGlobal": true}, "463892f8": {"codeEntityRedundancyNumForLocal": 0, "codeEntitySumForLobal": 1, "commitRedundancyForLocal": false, "codeEntityRedundancyNumForGlobal": 0, "codeEntitySumForGlobal": 1, "commitRedundancyForGlobal": false}, "489fc057": {"codeEntityRedundancyNumForLocal": 0, "codeEntitySumForLobal": 6, "commitRedundancyForLocal": false, "codeEntityRedundancyNumForGlobal": 0, "codeEntitySumForGlobal": 6, "commitRedundancyForGlobal": false}, "56c595ee": {"codeEntityRedundancyNumForLocal": 0, "codeEntitySumForLobal": 1, "commitRedundancyForLocal": false, "codeEntityRedundancyNumForGlobal": 0, "codeEntitySumForGlobal": 1, "commitRedundancyForGlobal": false}, "e3eea51f": {"codeEntityRedundancyNumForLocal": 3, "codeEntitySumForLobal": 3, "commitRedundancyForLocal": true, "codeEntityRedundancyNumForGlobal": 3, "codeEntitySumForGlobal": 3, "commitRedundancyForGlobal": true}, "9ceeb15b": {"codeEntityRedundancyNumForLocal": 0, "codeEntitySumForLobal": 0, "commitRedundancyForLocal": true, "codeEntityRedundancyNumForGlobal": 0, "codeEntitySumForGlobal": 0, "commitRedundancyForGlobal": true}, "1449ba6a": {"codeEntityRedundancyNumForLocal": 4, "codeEntitySumForLobal": 8, "commitRedundancyForLocal": false, "codeEntityRedundancyNumForGlobal": 4, "codeEntitySumForGlobal": 8, "commitRedundancyForGlobal": false}, "c636701f": {"codeEntityRedundancyNumForLocal": 16, "codeEntitySumForLobal": 32, "commitRedundancyForLocal": false, "codeEntityRedundancyNumForGlobal": 16, "codeEntitySumForGlobal": 32, "commitRedundancyForGlobal": false}, "cc90e854": {"codeEntityRedundancyNumForLocal": 202, "codeEntitySumForLobal": 322, "commitRedundancyForLocal": false, "codeEntityRedundancyNumForGlobal": 202, "codeEntitySumForGlobal": 322, "commitRedundancyForGlobal": false}, "d98fae04": {"codeEntityRedundancyNumForLocal": 2, "codeEntitySumForLobal": 2, "commitRedundancyForLocal": true, "codeEntityRedundancyNumForGlobal": 2, "codeEntitySumForGlobal": 2, "commitRedundancyForGlobal": true}, "894522fe": {"codeEntityRedundancyNumForLocal": 0, "codeEntitySumForLobal": 3, "commitRedundancyForLocal": false, "codeEntityRedundancyNumForGlobal": 0, "codeEntitySumForGlobal": 3, "commitRedundancyForGlobal": false}, "e899af43": {"codeEntityRedundancyNumForLocal": 1, "codeEntitySumForLobal": 2, "commitRedundancyForLocal": false, "codeEntityRedundancyNumForGlobal": 1, "codeEntitySumForGlobal": 2, "commitRedundancyForGlobal": false}, "04b60f6c": {"codeEntityRedundancyNumForLocal": 0, "codeEntitySumForLobal": 2, "commitRedundancyForLocal": false, "codeEntityRedundancyNumForGlobal": 0, "codeEntitySumForGlobal": 2, "commitRedundancyForGlobal": false}, "18f5ffcd": {"codeEntityRedundancyNumForLocal": 1, "codeEntitySumForLobal": 1, "commitRedundancyForLocal": true, "codeEntityRedundancyNumForGlobal": 1, "codeEntitySumForGlobal": 1, "commitRedundancyForGlobal": true}, "c2ddbdbc": {"codeEntityRedundancyNumForLocal": 1, "codeEntitySumForLobal": 19, "commitRedundancyForLocal": false, "codeEntityRedundancyNumForGlobal": 1, "codeEntitySumForGlobal": 19, "commitRedundancyForGlobal": false}, "bfad7c12": {"codeEntityRedundancyNumForLocal": 0, "codeEntitySumForLobal": 0, "commitRedundancyForLocal": true, "codeEntityRedundancyNumForGlobal": 0, "codeEntitySumForGlobal": 0, "commitRedundancyForGlobal": true}, "37f0e6b5": {"codeEntityRedundancyNumForLocal": 7, "codeEntitySumForLobal": 31, "commitRedundancyForLocal": false, "codeEntityRedundancyNumForGlobal": 20, "codeEntitySumForGlobal": 31, "commitRedundancyForGlobal": false}, "cf064286": {"codeEntityRedundancyNumForLocal": 10, "codeEntitySumForLobal": 21, "commitRedundancyForLocal": false, "codeEntityRedundancyNumForGlobal": 10, "codeEntitySumForGlobal": 21, "commitRedundancyForGlobal": false}, "a67e5b95": {"codeEntityRedundancyNumForLocal": 13, "codeEntitySumForLobal": 13, "commitRedundancyForLocal": true, "codeEntityRedundancyNumForGlobal": 13, "codeEntitySumForGlobal": 13, "commitRedundancyForGlobal": true}, "8dcd43be": {"codeEntityRedundancyNumForLocal": 7, "codeEntitySumForLobal": 59, "commitRedundancyForLocal": false, "codeEntityRedundancyNumForGlobal": 7, "codeEntitySumForGlobal": 59, "commitRedundancyForGlobal": false}, "6a55c82e": {"codeEntityRedundancyNumForLocal": 0, "codeEntitySumForLobal": 17, "commitRedundancyForLocal": false, "codeEntityRedundancyNumForGlobal": 0, "codeEntitySumForGlobal": 17, "commitRedundancyForGlobal": false}, "6a7b538b": {"codeEntityRedundancyNumForLocal": 0, "codeEntitySumForLobal": 0, "commitRedundancyForLocal": true, "codeEntityRedundancyNumForGlobal": 0, "codeEntitySumForGlobal": 0, "commitRedundancyForGlobal": true}, "bc746430": {"codeEntityRedundancyNumForLocal": 5, "codeEntitySumForLobal": 5, "commitRedundancyForLocal": true, "codeEntityRedundancyNumForGlobal": 5, "codeEntitySumForGlobal": 5, "commitRedundancyForGlobal": true}, "3ca0cfcc": {"codeEntityRedundancyNumForLocal": 10, "codeEntitySumForLobal": 106, "commitRedundancyForLocal": false, "codeEntityRedundancyNumForGlobal": 10, "codeEntitySumForGlobal": 106, "commitRedundancyForGlobal": false}, "120ac3ee": {"codeEntityRedundancyNumForLocal": 0, "codeEntitySumForLobal": 1, "commitRedundancyForLocal": false, "codeEntityRedundancyNumForGlobal": 0, "codeEntitySumForGlobal": 1, "commitRedundancyForGlobal": false}}}